Metadata-Version: 1.0
Name: distributions-egm
Version: 0.1
Summary: different distribution classes
Home-page: UNKNOWN
Author: UNKNOWN
Author-email: UNKNOWN
License: UNKNOWN
Platform: UNKNOWN
